testyles/__init__.py
testyles/styles.py
teplotstyles-0.0.3.dist-info/METADATA
teplotstyles-0.0.3.dist-info/WHEEL
teplotstyles-0.0.3.dist-info/top_level.txt
teplotstyles-0.0.3.dist-info/RECORD
