Metadata-Version: 2.1
Name: teplotstyles
Version: 0.0.3
Summary: Pacakge for quickly implementing matplotlib styles.
Author: Jack Minchin
License: UNKNOWN
Platform: UNKNOWN
Classifier: Programming Language :: Python :: 3
Classifier: License :: OSI Approved :: MIT License
Classifier: Operating System :: OS Independent
Requires-Python: >=3.6
Requires-Dist: matplotlib
